MANIFEST.in
README.rst
setup.py
django_voice.egg-info/PKG-INFO
django_voice.egg-info/SOURCES.txt
django_voice.egg-info/dependency_links.txt
django_voice.egg-info/not-zip-safe
django_voice.egg-info/requires.txt
django_voice.egg-info/top_level.txt
djangovoice/__init__.py
djangovoice/admin.py
djangovoice/compat.py
djangovoice/feeds.py
djangovoice/forms.py
djangovoice/mixins.py
djangovoice/models.py
djangovoice/settings.py
djangovoice/tests.py
djangovoice/urls.py
djangovoice/utils.py
djangovoice/views.py
djangovoice/fixtures/initial_data.json
djangovoice/migrations/0001_initial.py
djangovoice/migrations/0002_auto__add_field_feedback_email__add_field_feedback_slug.py
djangovoice/migrations/0003_auto__add_feedbackvote.py
djangovoice/migrations/__init__.py
djangovoice/static/djangovoice/css/bootstrap-responsive.min.css
djangovoice/static/djangovoice/css/bootstrap.min.css
djangovoice/static/djangovoice/css/dialog.css
djangovoice/static/djangovoice/css/style.css
djangovoice/static/djangovoice/img/dialog_close.png
djangovoice/static/djangovoice/img/glyphicons-halflings-white.png
djangovoice/static/djangovoice/img/glyphicons-halflings.png
djangovoice/static/djangovoice/img/loading.gif
djangovoice/static/djangovoice/img/rss.png
djangovoice/static/djangovoice/js/djangovoice.js
djangovoice/static/djangovoice/js/libs/bootstrap.min.js
djangovoice/static/djangovoice/js/libs/jquery-1.8.3.min.js
djangovoice/static/djangovoice/js/libs/modernizr-2.5.3-respond-1.1.0.min.js
djangovoice/static/djangovoice/less/dialog.less
djangovoice/static/djangovoice/less/helpers.less
djangovoice/static/djangovoice/less/style.less
djangovoice/templates/djangovoice/base.html
djangovoice/templates/djangovoice/delete.html
djangovoice/templates/djangovoice/detail.html
djangovoice/templates/djangovoice/form.html
djangovoice/templates/djangovoice/list.html
djangovoice/templates/djangovoice/signin.html
djangovoice/templates/djangovoice/widget.html
djangovoice/templates/djangovoice/includes/field.html
djangovoice/templates/djangovoice/includes/field_checkbox.html
djangovoice/templates/djangovoice/includes/navbottom.html
djangovoice/templates/djangovoice/includes/sidebar.html
