Metadata-Version: 1.1
Name: django-voice
Version: 0.5
Summary: A feedback application for Django
Home-page: https://github.com/gkmngrgn/django-voice
Author: Gökmen Görgen
Author-email: gokmen@alageek.com
License: BSD
Platform: any
Classifier: Programming Language :: Python
Classifier: Topic :: Software Development :: Libraries :: Python Modules
Classifier: Framework :: Django
Classifier: Environment :: Web Environment
